[
    {
        "entry": 123,
        "priority": "high",
        "todo": "take out the trash",
        "checked": false
    },
    {
        "entry": 222,
        "priority": "low",
        "todo": "take out the trash",
        "checked": false
    },
    {
        "entry": 333,
        "priority": "medium",
        "todo": "take out the trash",
        "checked": false
    },
    {
        "entry": 444,
        "priority": "high",
        "todo": "take out the trash",
        "checked": false
    },
    {
        "entry": 555,
        "priority": "medium",
        "todo": "take out the trash",
        "checked": false
    },
    {
        "entry": 666,
        "priority": "low",
        "todo": "take out the trash",
        "checked": false
    }
]